<?xml version="1.0" encoding="UTF-8"?><xfdf xmlns="http://ns.adobe.com/xfdf/" xml:space="preserve"><fields/><annots><square page="29" rect="66.760,298.686,403.940,323.206" color="#E44234" flags="print" name="e82b2b2d-2e6e-d84e-4bcd-e01d75c809ee" title="Guest" subject="矩形" date="D:20220408152551+08'00'" creationdate="D:20220408152550+08'00'"/><square page="29" rect="72.890,173.346,286.780,190.376" color="#E44234" flags="print" name="8ab65b5a-1c89-4782-f551-7ce3680207f1" title="Guest" subject="矩形" date="D:20220408152601+08'00'" creationdate="D:20220408152559+08'00'"/><square page="30" rect="77.650,315.716,281.330,341.606" color="#E44234" flags="print" name="85834ccf-a3b9-7d11-8338-c5fdce9dff94" title="Guest" subject="矩形" date="D:20220408152614+08'00'" creationdate="D:20220408152612+08'00'"/><square page="30" rect="59.260,113.406,438.680,264.626" color="#E44234" flags="print" name="a8cdbd73-be9b-b357-b341-a506576a1886" title="Guest" subject="矩形" date="D:20220408152653+08'00'" creationdate="D:20220408152651+08'00'"/><square page="33" rect="61.310,335.466,436.640,467.616" color="#E44234" flags="print" name="5ac530c2-55cd-e25a-66e5-bab38d9634f9" title="Guest" subject="矩形" date="D:20220408153117+08'00'" creationdate="D:20220408153114+08'00'"/><square page="42" rect="63.350,221.716,449.580,516.666" color="#E44234" flags="print" name="af776e2e-fa7c-1c24-d2d5-a1eaee9ef982" title="Guest" subject="矩形" date="D:20220408153653+08'00'" creationdate="D:20220408153647+08'00'"/><square page="44" rect="53.810,435.606,438,609.306" color="#E44234" flags="print" name="ac7ae064-ec67-1270-ba17-2acb0c742917" title="Guest" subject="矩形" date="D:20220408153727+08'00'" creationdate="D:20220408153725+08'00'"/><square page="47" rect="54.490,112.726,435.960,245.556" color="#E44234" flags="print" name="1cfe7cff-d5b0-a75a-d5b6-5c1a329cbf6c" title="Guest" subject="矩形" date="D:20220408153827+08'00'" creationdate="D:20220408153825+08'00'"/><square page="32" rect="32.360,148.486,450.430,365.616" color="#E44234" flags="print" name="8169c383-d2e7-c150-a042-d3b17d510e2d" title="Guest" subject="矩形" date="D:20220408154409+08'00'" creationdate="D:20220408154407+08'00'"/><square page="57" rect="57.900,344.326,435.100,609.986" color="#E44234" flags="print" name="9f15c5de-a8ca-efd1-9686-bc633d13e959" title="Guest" subject="矩形" date="D:20220408154537+08'00'" creationdate="D:20220408154535+08'00'"/><square page="58" rect="55.350,77.816,439.360,179.136" color="#E44234" flags="print" name="358540bc-3191-8899-0345-185899637a88" title="Guest" subject="矩形" date="D:20220408154549+08'00'" creationdate="D:20220408154547+08'00'"/><square page="60" rect="61.780,146.456,447.900,320.556" color="#E44234" flags="print" name="ade28ba1-ac2c-7c98-b362-8eec0d7d875f" title="Guest" subject="矩形" date="D:20220408155048+08'00'" creationdate="D:20220408155045+08'00'"/><square page="63" rect="54.760,510.816,435.260,602.076" color="#E44234" flags="print" name="45ef255d-9f96-276b-e4a7-a6215a0a0d42" title="Guest" subject="矩形" date="D:20220408155129+08'00'" creationdate="D:20220408155127+08'00'"/><square page="63" rect="70.910,296.696,406.480,399.186" color="#E44234" flags="print" name="14aea1da-20e1-a145-c2f9-5e1e07a25c86" title="Guest" subject="矩形" date="D:20220408155148+08'00'" creationdate="D:20220408155144+08'00'"/><square page="63" rect="77.220,270.716,227.460,288.266" color="#E44234" flags="print" name="4b525515-dc4c-c2c2-c42c-d5ac2ea03769" title="Guest" subject="矩形" date="D:20220408155202+08'00'" creationdate="D:20220408155201+08'00'"/><square page="63" rect="77.930,85.376,249.920,107.846" color="#E44234" flags="print" name="504607d8-3dc2-40ab-fd97-56ab9d8449d6" title="Guest" subject="矩形" date="D:20220408155208+08'00'" creationdate="D:20220408155207+08'00'"/><square page="64" rect="77.220,513.616,264.670,537.486" color="#E44234" flags="print" name="a0f73ad4-3528-9613-da2b-0cce1b8783e2" title="Guest" subject="矩形" date="D:20220408155218+08'00'" creationdate="D:20220408155217+08'00'"/><square page="64" rect="74.420,365.486,315.920,391.466" color="#E44234" flags="print" name="91a1559c-e204-13ff-a0d1-dc15e4f1142e" title="Guest" subject="矩形" date="D:20220408155226+08'00'" creationdate="D:20220408155223+08'00'"/><square page="89" rect="66.690,264.396,431.050,614.716" color="#E44234" flags="print" name="ff0e4dbf-80af-7da3-700f-3896a9ef21ef" title="Guest" subject="矩形" date="D:20220408161520+08'00'" creationdate="D:20220408161518+08'00'"/><square page="90" rect="53.350,431.486,439.470,604.186" color="#E44234" flags="print" name="4c23102d-84d9-8216-9d40-30c9b3165573" title="Guest" subject="矩形" date="D:20220408161537+08'00'" creationdate="D:20220408161536+08'00'"/><square page="99" rect="58.970,364.786,444.390,602.076" color="#E44234" flags="print" name="2fa2967a-0776-3db6-ce99-661a54c9dc83" title="Guest" subject="矩形" date="D:20220408162135+08'00'" creationdate="D:20220408162132+08'00'"/><square page="100" rect="58.270,50.976,442.280,475.716" color="#E44234" flags="print" name="bafdef09-530f-4c3f-4dd7-da8bda057d8d" title="Guest" subject="矩形" date="D:20220408162215+08'00'" creationdate="D:20220408162209+08'00'"/></annots><pages><defmtx matrix="1,0,0,-1,0,651.7747000000002"/><pgmtx matrix="1,0,0,-1,0,684.9158" page="1"/><pgmtx matrix="1,0,0,-1,0,684.9158" page="2"/><pgmtx matrix="1,0,0,-1,0,684.9158" page="3"/><pgmtx matrix="1,0,0,-1,0,684.9158" page="4"/><pgmtx matrix="1,0,0,-1,0,684.9158" page="5"/><pgmtx matrix="1,0,0,-1,0,684.9158" page="6"/><pgmtx matrix="1,0,0,-1,0,684.9158" page="7"/><pgmtx matrix="1,0,0,-1,0,684.9158" page="8"/><pgmtx matrix="1,0,0,-1,0,684.9158" page="9"/><pgmtx matrix="1,0,0,-1,0,684.9158" page="10"/><pgmtx matrix="1,0,0,-1,0,684.9158" page="11"/><pgmtx matrix="1,0,0,-1,0,684.9158" page="12"/><pgmtx matrix="1,0,0,-1,0,684.9158" page="13"/><pgmtx matrix="1,0,0,-1,0,684.9158" page="14"/><pgmtx matrix="1,0,0,-1,0,684.9158" page="15"/><pgmtx matrix="1,0,0,-1,0,684.9158" page="16"/><pgmtx matrix="1,0,0,-1,0,684.9158" page="17"/><pgmtx matrix="1,0,0,-1,0,684.9158" page="18"/><pgmtx matrix="1,0,0,-1,0,684.9158" page="19"/><pgmtx matrix="1,0,0,-1,0,684.9158" page="20"/><pgmtx matrix="1,0,0,-1,0,684.9158" page="21"/><pgmtx matrix="1,0,0,-1,0,684.9158" page="22"/><pgmtx matrix="1,0,0,-1,0,684.9158" page="23"/><pgmtx matrix="1,0,0,-1,0,684.9158" page="24"/><pgmtx matrix="1,0,0,-1,0,684.9158" page="25"/><pgmtx matrix="1,0,0,-1,0,684.9158" page="26"/><pgmtx matrix="1,0,0,-1,0,684.9158" page="27"/><pgmtx matrix="1,0,0,-1,0,684.9158" page="28"/><pgmtx matrix="1,0,0,-1,0,684.9158" page="29"/><pgmtx matrix="1,0,0,-1,0,684.9158" page="30"/><pgmtx matrix="1,0,0,-1,0,684.9158" page="31"/><pgmtx matrix="1,0,0,-1,0,684.9158" page="32"/><pgmtx matrix="1,0,0,-1,0,684.9158" page="33"/><pgmtx matrix="1,0,0,-1,0,684.9158" page="34"/><pgmtx matrix="1,0,0,-1,0,684.9158" page="35"/><pgmtx matrix="1,0,0,-1,0,684.9158" page="36"/><pgmtx matrix="1,0,0,-1,0,684.9158" page="37"/><pgmtx matrix="1,0,0,-1,0,684.9158" page="38"/><pgmtx matrix="1,0,0,-1,0,684.9158" page="39"/><pgmtx matrix="1,0,0,-1,0,684.9158" page="40"/><pgmtx matrix="1,0,0,-1,0,684.9158" page="41"/><pgmtx matrix="1,0,0,-1,0,684.9158" page="42"/><pgmtx matrix="1,0,0,-1,0,684.9158" page="43"/><pgmtx matrix="1,0,0,-1,0,684.9158" page="44"/><pgmtx matrix="1,0,0,-1,0,684.9158" page="45"/><pgmtx matrix="1,0,0,-1,0,684.9158" page="46"/><pgmtx matrix="1,0,0,-1,0,684.9158" page="47"/><pgmtx matrix="1,0,0,-1,0,684.9158" page="48"/><pgmtx matrix="1,0,0,-1,0,684.9158" page="49"/><pgmtx matrix="1,0,0,-1,0,684.9158" page="50"/><pgmtx matrix="1,0,0,-1,0,684.9158" page="51"/><pgmtx matrix="1,0,0,-1,0,684.9158" page="52"/><pgmtx matrix="1,0,0,-1,0,684.9158" page="53"/><pgmtx matrix="1,0,0,-1,0,684.9158" page="54"/><pgmtx matrix="1,0,0,-1,0,684.9158" page="55"/><pgmtx matrix="1,0,0,-1,0,684.9158" page="56"/><pgmtx matrix="1,0,0,-1,0,684.9158" page="57"/><pgmtx matrix="1,0,0,-1,0,684.9158" page="58"/><pgmtx matrix="1,0,0,-1,0,684.9158" page="59"/><pgmtx matrix="1,0,0,-1,0,684.9158" page="60"/><pgmtx matrix="1,0,0,-1,0,684.9158" page="61"/><pgmtx matrix="1,0,0,-1,0,684.9158" page="62"/><pgmtx matrix="1,0,0,-1,0,684.9158" page="63"/><pgmtx matrix="1,0,0,-1,0,684.9158" page="64"/><pgmtx matrix="1,0,0,-1,0,684.9158" page="65"/><pgmtx matrix="1,0,0,-1,0,684.9158" page="66"/><pgmtx matrix="1,0,0,-1,0,684.9158" page="67"/><pgmtx matrix="1,0,0,-1,0,684.9158" page="68"/><pgmtx matrix="1,0,0,-1,0,684.9158" page="69"/><pgmtx matrix="1,0,0,-1,0,684.9158" page="70"/><pgmtx matrix="1,0,0,-1,0,684.9158" page="71"/><pgmtx matrix="1,0,0,-1,0,684.9158" page="72"/><pgmtx matrix="1,0,0,-1,0,684.9158" page="73"/><pgmtx matrix="1,0,0,-1,0,684.9158" page="74"/><pgmtx matrix="1,0,0,-1,0,684.9158" page="75"/><pgmtx matrix="1,0,0,-1,0,684.9158" page="76"/><pgmtx matrix="1,0,0,-1,0,684.9158" page="77"/><pgmtx matrix="1,0,0,-1,0,684.9158" page="78"/><pgmtx matrix="1,0,0,-1,0,684.9158" page="79"/><pgmtx matrix="1,0,0,-1,0,684.9158" page="80"/><pgmtx matrix="1,0,0,-1,0,684.9158" page="81"/><pgmtx matrix="1,0,0,-1,0,684.9158" page="82"/><pgmtx matrix="1,0,0,-1,0,684.9158" page="83"/><pgmtx matrix="1,0,0,-1,0,684.9158" page="84"/><pgmtx matrix="1,0,0,-1,0,684.9158" page="85"/><pgmtx matrix="1,0,0,-1,0,684.9158" page="86"/><pgmtx matrix="1,0,0,-1,0,684.9158" page="87"/><pgmtx matrix="1,0,0,-1,0,684.9158" page="88"/><pgmtx matrix="1,0,0,-1,0,684.9158" page="89"/><pgmtx matrix="1,0,0,-1,0,684.9158" page="90"/><pgmtx matrix="1,0,0,-1,0,684.9158" page="91"/><pgmtx matrix="1,0,0,-1,0,684.9158" page="92"/><pgmtx matrix="1,0,0,-1,0,684.9158" page="93"/><pgmtx matrix="1,0,0,-1,0,684.9158" page="94"/><pgmtx matrix="1,0,0,-1,0,684.9158" page="95"/><pgmtx matrix="1,0,0,-1,0,684.9158" page="96"/><pgmtx matrix="1,0,0,-1,0,684.9158" page="97"/><pgmtx matrix="1,0,0,-1,0,684.9158" page="98"/><pgmtx matrix="1,0,0,-1,0,684.9158" page="99"/><pgmtx matrix="1,0,0,-1,0,684.9158" page="100"/><pgmtx matrix="1,0,0,-1,0,684.9158" page="101"/><pgmtx matrix="1,0,0,-1,0,684.9158" page="102"/><pgmtx matrix="1,0,0,-1,0,684.9158" page="103"/><pgmtx matrix="1,0,0,-1,0,684.9158" page="104"/><pgmtx matrix="1,0,0,-1,0,684.9158" page="105"/><pgmtx matrix="1,0,0,-1,0,684.9158" page="106"/><pgmtx matrix="1,0,0,-1,0,684.9158" page="107"/><pgmtx matrix="1,0,0,-1,0,684.9158" page="108"/><pgmtx matrix="1,0,0,-1,0,684.9158" page="109"/><pgmtx matrix="1,0,0,-1,0,684.9158" page="110"/><pgmtx matrix="1,0,0,-1,0,684.9158" page="111"/><pgmtx matrix="1,0,0,-1,0,684.9158" page="112"/><pgmtx matrix="1,0,0,-1,0,684.9158" page="113"/><pgmtx matrix="1,0,0,-1,0,684.9158" page="114"/><pgmtx matrix="1,0,0,-1,0,684.9158" page="115"/><pgmtx matrix="1,0,0,-1,0,684.9158" page="116"/><pgmtx matrix="1,0,0,-1,0,684.9158" page="117"/><pgmtx matrix="1,0,0,-1,0,684.9158" page="118"/><pgmtx matrix="1,0,0,-1,0,684.9158" page="119"/><pgmtx matrix="1,0,0,-1,0,684.9158" page="120"/><pgmtx matrix="1,0,0,-1,0,684.9158" page="121"/><pgmtx matrix="1,0,0,-1,0,684.9158" page="122"/><pgmtx matrix="1,0,0,-1,0,684.9158" page="123"/><pgmtx matrix="1,0,0,-1,0,684.9158" page="124"/><pgmtx matrix="1,0,0,-1,0,684.9158" page="125"/><pgmtx matrix="1,0,0,-1,0,684.9158" page="126"/><pgmtx matrix="1,0,0,-1,0,684.9158" page="127"/><pgmtx matrix="1,0,0,-1,0,684.9158" page="128"/><pgmtx matrix="1,0,0,-1,0,684.9158" page="129"/><pgmtx matrix="1,0,0,-1,0,684.9158" page="130"/><pgmtx matrix="1,0,0,-1,0,684.9158" page="131"/><pgmtx matrix="1,0,0,-1,0,684.9158" page="132"/><pgmtx matrix="1,0,0,-1,0,684.9158" page="133"/><pgmtx matrix="1,0,0,-1,0,684.9158" page="134"/><pgmtx matrix="1,0,0,-1,0,684.9158" page="135"/><pgmtx matrix="1,0,0,-1,0,684.9158" page="136"/><pgmtx matrix="1,0,0,-1,0,684.9158" page="137"/><pgmtx matrix="1,0,0,-1,0,684.9158" page="138"/><pgmtx matrix="1,0,0,-1,0,684.9158" page="139"/><pgmtx matrix="1,0,0,-1,0,684.9158" page="140"/><pgmtx matrix="1,0,0,-1,0,684.9158" page="141"/><pgmtx matrix="1,0,0,-1,0,684.9158" page="142"/><pgmtx matrix="1,0,0,-1,0,684.9158" page="143"/><pgmtx matrix="1,0,0,-1,0,684.9158" page="144"/><pgmtx matrix="1,0,0,-1,0,684.9158" page="145"/><pgmtx matrix="1,0,0,-1,0,684.9158" page="146"/><pgmtx matrix="1,0,0,-1,0,684.9158" page="147"/><pgmtx matrix="1,0,0,-1,0,684.9158" page="148"/><pgmtx matrix="1,0,0,-1,0,684.9158" page="149"/><pgmtx matrix="1,0,0,-1,0,684.9158" page="150"/><pgmtx matrix="1,0,0,-1,0,684.9158" page="151"/><pgmtx matrix="1,0,0,-1,0,684.9158" page="152"/><pgmtx matrix="1,0,0,-1,0,684.9158" page="153"/><pgmtx matrix="1,0,0,-1,0,684.9158" page="154"/><pgmtx matrix="1,0,0,-1,0,684.9158" page="155"/><pgmtx matrix="1,0,0,-1,0,684.9158" page="156"/><pgmtx matrix="1,0,0,-1,0,684.9158" page="157"/><pgmtx matrix="1,0,0,-1,0,684.9158" page="158"/><pgmtx matrix="1,0,0,-1,0,684.9158" page="159"/><pgmtx matrix="1,0,0,-1,0,684.9158" page="160"/><pgmtx matrix="1,0,0,-1,0,684.9158" page="161"/><pgmtx matrix="1,0,0,-1,0,684.9158" page="162"/><pgmtx matrix="1,0,0,-1,0,684.9158" page="163"/><pgmtx matrix="1,0,0,-1,0,684.9158" page="164"/><pgmtx matrix="1,0,0,-1,0,684.9158" page="165"/><pgmtx matrix="1,0,0,-1,0,684.9158" page="166"/><pgmtx matrix="1,0,0,-1,0,684.9158" page="167"/><pgmtx matrix="1,0,0,-1,0,684.9158" page="168"/><pgmtx matrix="1,0,0,-1,0,684.9158" page="169"/><pgmtx matrix="1,0,0,-1,0,684.9158" page="170"/><pgmtx matrix="1,0,0,-1,0,684.9158" page="171"/><pgmtx matrix="1,0,0,-1,0,684.9158" page="172"/><pgmtx matrix="1,0,0,-1,0,684.9158" page="173"/><pgmtx matrix="1,0,0,-1,0,684.9158" page="174"/><pgmtx matrix="1,0,0,-1,0,684.9158" page="175"/><pgmtx matrix="1,0,0,-1,0,684.9158" page="176"/><pgmtx matrix="1,0,0,-1,0,684.9158" page="177"/><pgmtx matrix="1,0,0,-1,0,684.9158" page="178"/><pgmtx matrix="1,0,0,-1,0,684.9158" page="179"/><pgmtx matrix="1,0,0,-1,0,684.9158" page="180"/><pgmtx matrix="1,0,0,-1,0,684.9158" page="181"/><pgmtx matrix="1,0,0,-1,0,684.9158" page="182"/><pgmtx matrix="1,0,0,-1,0,684.9158" page="183"/><pgmtx matrix="1,0,0,-1,0,684.9158" page="184"/><pgmtx matrix="1,0,0,-1,0,684.9158" page="185"/><pgmtx matrix="1,0,0,-1,0,684.9158" page="186"/><pgmtx matrix="1,0,0,-1,0,684.9158" page="187"/><pgmtx matrix="1,0,0,-1,0,684.9158" page="188"/><pgmtx matrix="1,0,0,-1,0,684.9158" page="189"/><pgmtx matrix="1,0,0,-1,0,684.9158" page="190"/><pgmtx matrix="1,0,0,-1,0,684.9158" page="191"/><pgmtx matrix="1,0,0,-1,0,684.9158" page="192"/><pgmtx matrix="1,0,0,-1,0,684.9158" page="193"/><pgmtx matrix="1,0,0,-1,0,684.9158" page="194"/><pgmtx matrix="1,0,0,-1,0,684.9158" page="195"/><pgmtx matrix="1,0,0,-1,0,684.9158" page="196"/><pgmtx matrix="1,0,0,-1,0,684.9158" page="197"/><pgmtx matrix="1,0,0,-1,0,684.9158" page="198"/><pgmtx matrix="1,0,0,-1,0,684.9158" page="199"/><pgmtx matrix="1,0,0,-1,0,684.9158" page="200"/><pgmtx matrix="1,0,0,-1,0,684.9158" page="201"/><pgmtx matrix="1,0,0,-1,0,684.9158" page="202"/><pgmtx matrix="1,0,0,-1,0,684.9158" page="203"/><pgmtx matrix="1,0,0,-1,0,684.9158" page="204"/><pgmtx matrix="1,0,0,-1,0,684.9158" page="205"/><pgmtx matrix="1,0,0,-1,0,684.9158" page="206"/><pgmtx matrix="1,0,0,-1,0,684.9158" page="207"/><pgmtx matrix="1,0,0,-1,0,684.9158" page="208"/><pgmtx matrix="1,0,0,-1,0,684.9158" page="209"/><pgmtx matrix="1,0,0,-1,0,684.9158" page="210"/><pgmtx matrix="1,0,0,-1,0,684.9158" page="211"/><pgmtx matrix="1,0,0,-1,0,684.9158" page="212"/><pgmtx matrix="1,0,0,-1,0,684.9158" page="213"/><pgmtx matrix="1,0,0,-1,0,684.9158" page="214"/><pgmtx matrix="1,0,0,-1,0,684.9158" page="215"/><pgmtx matrix="1,0,0,-1,0,684.9158" page="216"/><pgmtx matrix="1,0,0,-1,0,684.9158" page="217"/><pgmtx matrix="1,0,0,-1,0,684.9158" page="218"/><pgmtx matrix="1,0,0,-1,0,684.9158" page="219"/><pgmtx matrix="1,0,0,-1,0,684.9158" page="220"/><pgmtx matrix="1,0,0,-1,0,684.9158" page="221"/><pgmtx matrix="1,0,0,-1,0,684.9158" page="222"/><pgmtx matrix="1,0,0,-1,0,684.9158" page="223"/><pgmtx matrix="1,0,0,-1,0,684.9158" page="224"/><pgmtx matrix="1,0,0,-1,0,684.9158" page="225"/><pgmtx matrix="1,0,0,-1,0,684.9158" page="226"/><pgmtx matrix="1,0,0,-1,0,684.9158" page="227"/><pgmtx matrix="1,0,0,-1,0,684.9158" page="228"/><pgmtx matrix="1,0,0,-1,0,684.9158" page="229"/><pgmtx matrix="1,0,0,-1,0,684.9158" page="230"/><pgmtx matrix="1,0,0,-1,0,684.9158" page="231"/><pgmtx matrix="1,0,0,-1,0,684.9158" page="232"/><pgmtx matrix="1,0,0,-1,0,684.9158" page="233"/><pgmtx matrix="1,0,0,-1,0,684.9158" page="234"/><pgmtx matrix="1,0,0,-1,0,684.9158" page="235"/><pgmtx matrix="1,0,0,-1,0,684.9158" page="236"/><pgmtx matrix="1,0,0,-1,0,684.9158" page="237"/><pgmtx matrix="1,0,0,-1,0,684.9158" page="238"/><pgmtx matrix="1,0,0,-1,0,684.9158" page="239"/><pgmtx matrix="1,0,0,-1,0,684.9158" page="240"/><pgmtx matrix="1,0,0,-1,0,684.9158" page="241"/><pgmtx matrix="1,0,0,-1,0,684.9158" page="242"/><pgmtx matrix="1,0,0,-1,0,684.9158" page="243"/><pgmtx matrix="1,0,0,-1,0,684.9158" page="244"/><pgmtx matrix="1,0,0,-1,0,684.9158" page="245"/><pgmtx matrix="1,0,0,-1,0,684.9158" page="246"/><pgmtx matrix="1,0,0,-1,0,684.9158" page="247"/><pgmtx matrix="1,0,0,-1,0,684.9158" page="248"/><pgmtx matrix="1,0,0,-1,0,684.9158" page="249"/><pgmtx matrix="1,0,0,-1,0,684.9158" page="250"/><pgmtx matrix="1,0,0,-1,0,684.9158" page="251"/><pgmtx matrix="1,0,0,-1,0,684.9158" page="252"/><pgmtx matrix="1,0,0,-1,0,684.9158" page="253"/><pgmtx matrix="1,0,0,-1,0,684.9158" page="254"/><pgmtx matrix="1,0,0,-1,0,684.9158" page="255"/><pgmtx matrix="1,0,0,-1,0,684.9158" page="256"/><pgmtx matrix="1,0,0,-1,0,684.9158" page="257"/><pgmtx matrix="1,0,0,-1,0,684.9158" page="258"/><pgmtx matrix="1,0,0,-1,0,684.9158" page="259"/><pgmtx matrix="1,0,0,-1,0,684.9158" page="260"/><pgmtx matrix="1,0,0,-1,0,684.9158" page="261"/><pgmtx matrix="1,0,0,-1,0,684.9158" page="262"/><pgmtx matrix="1,0,0,-1,0,684.9158" page="263"/><pgmtx matrix="1,0,0,-1,0,684.9158" page="264"/><pgmtx matrix="1,0,0,-1,0,684.9158" page="265"/><pgmtx matrix="1,0,0,-1,0,684.9158" page="266"/><pgmtx matrix="1,0,0,-1,0,684.9158" page="267"/><pgmtx matrix="1,0,0,-1,0,684.9158" page="268"/><pgmtx matrix="1,0,0,-1,0,684.9158" page="269"/><pgmtx matrix="1,0,0,-1,0,684.9158" page="270"/><pgmtx matrix="1,0,0,-1,0,684.9158" page="271"/><pgmtx matrix="1,0,0,-1,0,684.9158" page="272"/><pgmtx matrix="1,0,0,-1,0,684.9158" page="273"/><pgmtx matrix="1,0,0,-1,0,684.9158" page="274"/><pgmtx matrix="1,0,0,-1,0,684.9158" page="275"/><pgmtx matrix="1,0,0,-1,0,684.9158" page="276"/><pgmtx matrix="1,0,0,-1,0,684.9158" page="277"/><pgmtx matrix="1,0,0,-1,0,684.9158" page="278"/><pgmtx matrix="1,0,0,-1,0,684.9158" page="279"/><pgmtx matrix="1,0,0,-1,0,684.9158" page="280"/><pgmtx matrix="1,0,0,-1,0,684.9158" page="281"/><pgmtx matrix="1,0,0,-1,0,684.9158" page="282"/><pgmtx matrix="1,0,0,-1,0,684.9158" page="283"/><pgmtx matrix="1,0,0,-1,0,684.9158" page="284"/><pgmtx matrix="1,0,0,-1,0,684.9158" page="285"/><pgmtx matrix="1,0,0,-1,0,684.9158" page="286"/><pgmtx matrix="1,0,0,-1,0,684.9158" page="287"/><pgmtx matrix="1,0,0,-1,0,684.9158" page="288"/><pgmtx matrix="1,0,0,-1,0,684.9158" page="289"/><pgmtx matrix="1,0,0,-1,0,684.9158" page="290"/><pgmtx matrix="1,0,0,-1,0,684.9158" page="291"/><pgmtx matrix="1,0,0,-1,0,684.9158" page="292"/><pgmtx matrix="1,0,0,-1,0,684.9158" page="293"/><pgmtx matrix="1,0,0,-1,0,684.9158" page="294"/><pgmtx matrix="1,0,0,-1,0,684.9158" page="295"/><pgmtx matrix="1,0,0,-1,0,684.9158" page="296"/><pgmtx matrix="1,0,0,-1,0,684.9158" page="297"/><pgmtx matrix="1,0,0,-1,0,684.9158" page="298"/><pgmtx matrix="1,0,0,-1,0,684.9158" page="299"/><pgmtx matrix="1,0,0,-1,0,684.9158" page="300"/><pgmtx matrix="1,0,0,-1,0,684.9158" page="301"/><pgmtx matrix="1,0,0,-1,0,684.9158" page="302"/><pgmtx matrix="1,0,0,-1,0,684.9158" page="303"/><pgmtx matrix="1,0,0,-1,0,684.9158" page="304"/><pgmtx matrix="1,0,0,-1,0,684.9158" page="305"/><pgmtx matrix="1,0,0,-1,0,684.9158" page="306"/><pgmtx matrix="1,0,0,-1,0,684.9158" page="307"/><pgmtx matrix="1,0,0,-1,0,684.9158" page="308"/><pgmtx matrix="1,0,0,-1,0,684.9158" page="309"/></pages></xfdf>